[{"__type__":"cc.SpriteFrame","content":{"name":"gravity_switch_boost","texture":"0ePfe36pZK96ZO/ftjQz33","rect":[0,0,52,53],"offset":[0,0],"originalSize":[52,53],"capInsets":[0,0,0,0]}},[{"__type__":"cc.Prefab","_name":"gravity_reverse_boost","data":{"__id__":1}},{"__type__":"cc.Node","_name":"gravity_reverse_boost","_level":1,"_components":[{"__type__":"7d803CQyG5M/JXGf44Nwit4","node":{"__id__":1}},{"__type__":"cc.Sprite","node":{"__id__":1},"_spriteFrame":{"__uuid__":"97k53kcGtBZrCSs4ZmTsz1"}},{"__type__":"cc.BoxCollider","node":{"__id__":1},"_size":{"__type__":"cc.Size","width":52,"height":53}},{"__type__":"cc.Animation","node":{"__id__":1},"_defaultClip":{"__uuid__":"87SPSodpVD9KbwZG65Rzvo"},"_clips":[{"__uuid__":"87SPSodpVD9KbwZG65Rzvo"}],"playOnLoad":true},{"__type__":"cc.AudioSource","node":{"__id__":1},"_clip":{"__uuid__":"ab9ltxdZFBRpcswPi1GF61"},"_volume":0.3,"preload":true}],"_prefab":{"__type__":"cc.PrefabInfo","root":{"__id__":1},"asset":{"__uuid__":"aafeChb/9LfJRN/3U5Z3YU"},"fileId":"14R+CFRipH4p9zkMsqsEHZ"},"_contentSize":{"__type__":"cc.Size","width":52,"height":53},"_scale":{"__type__":"cc.Vec3","x":0.61,"y":0.61,"z":1}}]]