[{"__type__":"cc.SpriteFrame","content":{"name":"part_9_b","texture":"b2AuqFJf5OS4eReSBfVRMt","rect":[0,7,1142,1128],"offset":[0,0],"originalSize":[1142,1142],"capInsets":[0,0,0,0]}},[{"__type__":"cc.Prefab","_name":"part9","data":{"__id__":1}},{"__type__":"cc.Node","_name":"part","_children":[{"__type__":"cc.Node","_name":"player","_parent":{"__id__":1},"_level":2,"_prefab":{"__type__":"cc.PrefabInfo","root":{"__id__":1},"asset":{"__uuid__":"2f87xfPHdPopd9JBp6o5vQ"},"fileId":"a2n98JfbdPBJdsykrPs7/p"},"_contentSize":{"__type__":"cc.Size","width":74.307,"height":161.543},"_position":{"__type__":"cc.Vec3","x":8.7,"y":15.5},"_scale":{"__type__":"cc.Vec3","x":1,"y":1,"z":1}},{"__id__":2},{"__id__":3},{"__id__":4}],"_level":1,"_components":[{"__type__":"fcea8sx5ChGA7olOUrbkjrJ","node":{"__id__":1}},{"__type__":"2a5aceSEktA4rV1jy+c+yYT","node":{"__id__":1}}],"_prefab":{"__type__":"cc.PrefabInfo","root":{"__id__":1},"asset":{"__uuid__":"2f87xfPHdPopd9JBp6o5vQ"},"fileId":"464sLKRxZIp5hCRP1RgZWo"},"_scale":{"__type__":"cc.Vec3","x":1,"y":1,"z":1}},{"__type__":"cc.Node","_name":"aabb","_parent":{"__id__":1},"_level":2,"_components":[{"__type__":"cc.Sprite","node":{"__id__":2},"_spriteFrame":{"__uuid__":"79T/jlgKhMkIi9G0TVu8EZ"},"_sizeMode":0}],"_prefab":{"__type__":"cc.PrefabInfo","root":{"__id__":1},"asset":{"__uuid__":"2f87xfPHdPopd9JBp6o5vQ"},"fileId":"1eDpXwmkdIJrUZAWpahHfK"},"_opacity":100,"_contentSize":{"__type__":"cc.Size","width":510,"height":518},"_scale":{"__type__":"cc.Vec3","x":1,"y":1,"z":1}},{"__type__":"cc.Node","_name":"ground","_parent":{"__id__":1},"_level":2,"_components":[{"__type__":"cc.Sprite","node":{"__id__":3},"_spriteFrame":{"__uuid__":"9bboNcAThGSaTG0r5tQvmU"},"_sizeMode":0,"_isTrimmedMode":false},{"__type__":"cc.RigidBody","node":{"__id__":3},"_type":0},{"__type__":"cc.PhysicsPolygonCollider","node":{"__id__":3},"_offset":{"__type__":"cc.Vec2","x":6.5,"y":6.7},"points":[{"__type__":"cc.Vec2","x":-39.46196341463415,"y":17.256},{"__type__":"cc.Vec2","x":-45.0424430894309,"y":14.601230769230767},{"__type__":"cc.Vec2","x":-49.0285,"y":7.698830769230767},{"__type__":"cc.Vec2","x":-48.49702574525745,"y":-9.557169230769231},{"__type__":"cc.Vec2","x":-45.30818021680217,"y":-14.335753846153846},{"__type__":"cc.Vec2","x":-40.524911924119245,"y":-16.990523076923076},{"__type__":"cc.Vec2","x":39.461963414634134,"y":-17.256},{"__type__":"cc.Vec2","x":45.308180216802164,"y":-14.335753846153846},{"__type__":"cc.Vec2","x":49.02849999999999,"y":-7.698830769230771},{"__type__":"cc.Vec2","x":48.49702574525744,"y":9.55716923076923},{"__type__":"cc.Vec2","x":45.308180216802164,"y":14.335753846153843},{"__type__":"cc.Vec2","x":40.52491192411923,"y":16.990523076923076}]}],"_prefab":{"__type__":"cc.PrefabInfo","root":{"__id__":1},"asset":{"__uuid__":"2f87xfPHdPopd9JBp6o5vQ"},"fileId":"c5EXndzeZB5pgBy2cYPQIq"},"_contentSize":{"__type__":"cc.Size","width":111.61,"height":48.065},"_position":{"__type__":"cc.Vec3","y":-102},"_scale":{"__type__":"cc.Vec3","x":1.54,"y":1.54,"z":1}},{"__type__":"cc.Node","_name":"ground","_parent":{"__id__":1},"_children":[{"__id__":5}],"_level":2,"_components":[{"__type__":"cc.Sprite","node":{"__id__":4},"_spriteFrame":{"__uuid__":"16pfMzJ3VBzLPfjK13eQ/h"},"_sizeMode":0,"_isTrimmedMode":false},{"__type__":"cc.RigidBody","node":{"__id__":4},"_type":0},{"__type__":"cc.PhysicsPolygonCollider","node":{"__id__":4},"_offset":{"__type__":"cc.Vec2","x":-2.5,"y":-13.2},"points":[{"__type__":"cc.Vec2","x":-30.792503267973842,"y":162.457},{"__type__":"cc.Vec2","x":-36.63246078431372,"y":159.53702124183008},{"__type__":"cc.Vec2","x":-40.34879738562091,"y":152.90070588235295},{"__type__":"cc.Vec2","x":-39.81789215686274,"y":135.64628594771244},{"__type__":"cc.Vec2","x":-36.63246078431372,"y":130.8681388888889},{"__type__":"cc.Vec2","x":-31.854313725490186,"y":128.21361274509803},{"__type__":"cc.Vec2","x":48.312375816993466,"y":127.94816013071897},{"__type__":"cc.Vec2","x":55.47959640522876,"y":132.4608545751634},{"__type__":"cc.Vec2","x":57.868669934640536,"y":138.30081209150325},{"__type__":"cc.Vec2","x":57.07231209150328,"y":155.02432679738564},{"__type__":"cc.Vec2","x":53.35597549019607,"y":160.06792647058825},{"__type__":"cc.Vec2","x":49.37418627450981,"y":162.19154738562094}]},{"__type__":"cc.PhysicsPolygonCollider","node":{"__id__":4},"_offset":{"__type__":"cc.Vec2","x":-2.6,"y":-268},"points":[{"__type__":"cc.Vec2","x":-30.792503267973842,"y":162.457},{"__type__":"cc.Vec2","x":-32.650671568627445,"y":161.92609477124182},{"__type__":"cc.Vec2","x":-35.30519771241829,"y":160.59883169934642},{"__type__":"cc.Vec2","x":-36.10155555555555,"y":159.53702124183008},{"__type__":"cc.Vec2","x":-36.63246078431372,"y":159.53702124183008},{"__type__":"cc.Vec2","x":-37.42881862745098,"y":158.7406633986928},{"__type__":"cc.Vec2","x":-37.42881862745098,"y":158.20975816993462},{"__type__":"cc.Vec2","x":-38.49062908496731,"y":157.4134003267974},{"__type__":"cc.Vec2","x":-40.34879738562091,"y":152.90070588235295},{"__type__":"cc.Vec2","x":-40.34879738562091,"y":137.50445424836602},{"__type__":"cc.Vec2","x":-39.81789215686274,"y":135.64628594771244},{"__type__":"cc.Vec2","x":-38.49062908496731,"y":132.99175980392158},{"__type__":"cc.Vec2","x":-37.42881862745098,"y":132.1954019607843},{"__type__":"cc.Vec2","x":-37.42881862745098,"y":131.66449673202612},{"__type__":"cc.Vec2","x":-36.63246078431372,"y":130.8681388888889},{"__type__":"cc.Vec2","x":-36.10155555555555,"y":130.8681388888889},{"__type__":"cc.Vec2","x":-35.30519771241829,"y":129.80632843137255},{"__type__":"cc.Vec2","x":-31.854313725490186,"y":128.21361274509803},{"__type__":"cc.Vec2","x":48.312375816993466,"y":127.94816013071897},{"__type__":"cc.Vec2","x":51.76325980392156,"y":129.27542320261438},{"__type__":"cc.Vec2","x":55.47959640522876,"y":132.4608545751634},{"__type__":"cc.Vec2","x":57.07231209150328,"y":135.38083333333333},{"__type__":"cc.Vec2","x":57.868669934640536,"y":138.30081209150325},{"__type__":"cc.Vec2","x":57.868669934640536,"y":152.10434803921567},{"__type__":"cc.Vec2","x":57.07231209150328,"y":155.02432679738564},{"__type__":"cc.Vec2","x":55.47959640522876,"y":157.94430555555556},{"__type__":"cc.Vec2","x":53.35597549019607,"y":160.06792647058825},{"__type__":"cc.Vec2","x":49.37418627450981,"y":162.19154738562094}]},{"__type__":"cc.PhysicsPolygonCollider","node":{"__id__":4},"_offset":{"__type__":"cc.Vec2","x":-104.8,"y":-84.1},"points":[{"__type__":"cc.Vec2","x":1,"y":129.8},{"__type__":"cc.Vec2","x":-2.49,"y":134.97},{"__type__":"cc.Vec2","x":-7.66,"y":137.8},{"__type__":"cc.Vec2","x":-26.13,"y":137.8},{"__type__":"cc.Vec2","x":-30.96,"y":133.87},{"__type__":"cc.Vec2","x":-33.27,"y":128.13},{"__type__":"cc.Vec2","x":-33.5,"y":49.6},{"__type__":"cc.Vec2","x":-31.1,"y":44.3},{"__type__":"cc.Vec2","x":-25.6,"y":39.9},{"__type__":"cc.Vec2","x":-7.9,"y":39.8},{"__type__":"cc.Vec2","x":-2.6,"y":42.5},{"__type__":"cc.Vec2","x":1.4,"y":50.2}]},{"__type__":"cc.PhysicsPolygonCollider","node":{"__id__":4},"_offset":{"__type__":"cc.Vec2","x":92.7,"y":-108.8},"points":[{"__type__":"cc.Vec2","x":31.1,"y":162.4},{"__type__":"cc.Vec2","x":27,"y":159.4},{"__type__":"cc.Vec2","x":23.7,"y":154.1},{"__type__":"cc.Vec2","x":23.8,"y":73.4},{"__type__":"cc.Vec2","x":26.4,"y":68},{"__type__":"cc.Vec2","x":31,"y":65.2},{"__type__":"cc.Vec2","x":49.6,"y":64.9},{"__type__":"cc.Vec2","x":53.8,"y":67.6},{"__type__":"cc.Vec2","x":57.9,"y":73.2},{"__type__":"cc.Vec2","x":58,"y":153.6},{"__type__":"cc.Vec2","x":53.8,"y":160.1},{"__type__":"cc.Vec2","x":48.6,"y":162.9}]},{"__type__":"cc.Animation","node":{"__id__":4},"_defaultClip":{"__uuid__":"58JQyI4lBBz6Lf6TZHZsyV"},"_clips":[{"__uuid__":"58JQyI4lBBz6Lf6TZHZsyV"}],"playOnLoad":true},{"__type__":"351ef8HVclPa5lFKxBtJSFE","node":{"__id__":4}}],"_prefab":{"__type__":"cc.PrefabInfo","root":{"__id__":1},"asset":{"__uuid__":"2f87xfPHdPopd9JBp6o5vQ"},"fileId":"46oSpidRhJuYdC01f8uAJY"},"_contentSize":{"__type__":"cc.Size","width":303.204,"height":303.204},"_position":{"__type__":"cc.Vec3","y":-2},"_scale":{"__type__":"cc.Vec3","x":1.54,"y":1.54,"z":1}},{"__type__":"cc.Node","_name":"ring","_parent":{"__id__":4},"_level":3,"_components":[{"__type__":"cc.Sprite","node":{"__id__":5},"_spriteFrame":{"__uuid__":"ceDPnicmhFo6+gIKxb1SQv"}},{"__type__":"cc.RigidBody","node":{"__id__":5},"_type":0}],"_prefab":{"__type__":"cc.PrefabInfo","root":{"__id__":1},"asset":{"__uuid__":"2f87xfPHdPopd9JBp6o5vQ"},"fileId":"53+JDQa0VGEYmq582BlV95"},"_contentSize":{"__type__":"cc.Size","width":1104,"height":1104},"_scale":{"__type__":"cc.Vec3","x":0.2402597,"y":0.2402597,"z":1},"groupIndex":4}],{"__type__":"cc.SpriteFrame","content":{"name":"block","texture":"011DGUftxIWrUhm+HiTTtv","rect":[0,0,377,377],"offset":[0,0],"originalSize":[377,377],"capInsets":[0,0,0,0]}},{"__type__":"cc.SpriteFrame","content":{"name":"part_9_a","texture":"2cQe0AY3hDU4NnVQSq+t0l","rect":[0,0,421,181],"offset":[0,0],"originalSize":[421,181],"capInsets":[0,0,0,0]}},{"__type__":"cc.SpriteFrame","content":{"name":"part_4_b_ring","texture":"318J7Y6PpL0rLjiLkBrD7G","rect":[0,0,1104,1104],"offset":[0,0],"originalSize":[1104,1104],"capInsets":[0,0,0,0]}}]